xiaozhi_client/__init__.py
xiaozhi_client/client.py
xiaozhi_client/types.py
xiaozhi_client/utils/__init__.py
xiaozhi_client/utils/wav.py
xiaozhi_client-0.1.5.dist-info/LICENSE
xiaozhi_client-0.1.5.dist-info/METADATA
xiaozhi_client-0.1.5.dist-info/WHEEL
xiaozhi_client-0.1.5.dist-info/top_level.txt
xiaozhi_client-0.1.5.dist-info/RECORD
