Metadata-Version: 2.2
Name: xiaozhi-client
Version: 0.1.5
Summary: A Python client library for Xiaozhi AI assistant
Author-email: Eric <eric230308@gmail.com>
License: MIT License
Project-URL: Homepage, https://github.com/eric0308/xiaozhi-client
Project-URL: Bug Tracker, https://github.com/eric0308/xiaozhi-client/issues
Classifier: Programming Language :: Python :: 3
Classifier: License :: OSI Approved :: MIT License
Classifier: Operating System :: OS Independent
Requires-Python: >=3.10
License-File: LICENSE
Requires-Dist: websockets==10.4
Requires-Dist: opuslib==3.0.1
Requires-Dist: numpy==2.2.3
Requires-Dist: sounddevice==0.5.1
Requires-Dist: loguru==0.7.3
Requires-Dist: pyaudio==0.2.14
Requires-Dist: Pillow==10.2.0
